setup.py
usage/__init__.py
usage/eventloop.py
usage/model.py
usage/runner.py
usage.egg-info/PKG-INFO
usage.egg-info/SOURCES.txt
usage.egg-info/dependency_links.txt
usage.egg-info/entry_points.txt
usage.egg-info/requires.txt
usage.egg-info/top_level.txt