Metadata-Version: 1.1
Name: usage
Version: 0.0.2
Summary: Usage
Home-page: https://github.com/xlzd/usage
Author: xlzd
Author-email: i@xlzd.me
License: WTFPL
Download-URL: https://github.com/xlzd/usage
Platform: UNKNOWN
